{
  "configurations": [
    {
      "directories": [
        {
          "build": ".",
          "jsonFile": "directory-.-Debug-f5ebdc15457944623624.json",
          "minimumCMakeVersion": {
            "string": "3.22"
          },
          "projectIndex": 0,
          "source": ".",
          "targetIndexes": [
            0
          ]
        }
      ],
      "name": "Debug",
      "projects": [
        {
          "directoryIndexes": [
            0
          ],
          "name": "LinuxCC",
          "targetIndexes": [
            0
          ]
        }
      ],
      "targets": [
        {
          "directoryIndex": 0,
          "id": "LinuxCC::@6890427a1f51a3e7e1df",
          "jsonFile": "target-LinuxCC-Debug-aa6b9927daa6616602a7.json",
          "name": "LinuxCC",
          "projectIndex": 0
        }
      ]
    }
  ],
  "kind": "codemodel",
  "paths": {
    "build": "/root/LinuxCC/cmake-build-debug",
    "source": "/root/LinuxCC"
  },
  "version": {
    "major": 2,
    "minor": 3
  }
}
